deepget/__init__.py
deepget-1.0.1.dist-info/METADATA
deepget-1.0.1.dist-info/WHEEL
deepget-1.0.1.dist-info/top_level.txt
deepget-1.0.1.dist-info/RECORD
