Metadata-Version: 2.1
Name: deepget
Version: 1.0.1
Summary: Get values from a dict using `a.dotted.string.like.this`
Home-page: UNKNOWN
Author: UNKNOWN
Author-email: UNKNOWN
License: UNKNOWN
Platform: UNKNOWN
